LICENSE.txt
MANIFEST.in
README.rst
bootstrap.py
buildout.cfg
setup.py
versions.cfg
cmsplugin_zinnia/__init__.py
cmsplugin_zinnia/admin.py
cmsplugin_zinnia/cms_app.py
cmsplugin_zinnia/cms_plugins.py
cmsplugin_zinnia/cms_toolbar.py
cmsplugin_zinnia/forms.py
cmsplugin_zinnia/menu.py
cmsplugin_zinnia/models.py
cmsplugin_zinnia/placeholder.py
cmsplugin_zinnia/settings.py
cmsplugin_zinnia.egg-info/PKG-INFO
cmsplugin_zinnia.egg-info/SOURCES.txt
cmsplugin_zinnia.egg-info/dependency_links.txt
cmsplugin_zinnia.egg-info/not-zip-safe
cmsplugin_zinnia.egg-info/top_level.txt
cmsplugin_zinnia/locale/fr/LC_MESSAGES/django.mo
cmsplugin_zinnia/locale/fr/LC_MESSAGES/django.po
cmsplugin_zinnia/migrations/0001_initial.py
cmsplugin_zinnia/migrations/__init__.py
cmsplugin_zinnia/static/cmsplugin_zinnia/img/plugin.png
cmsplugin_zinnia/templates/cmsplugin_zinnia/authors_published.html
cmsplugin_zinnia/templates/cmsplugin_zinnia/categories_published.html
cmsplugin_zinnia/templates/cmsplugin_zinnia/categories_tree.html
cmsplugin_zinnia/templates/cmsplugin_zinnia/entries_archives_tree.html
cmsplugin_zinnia/templates/cmsplugin_zinnia/entries_calendar.html
cmsplugin_zinnia/templates/cmsplugin_zinnia/entries_random.html
cmsplugin_zinnia/templates/cmsplugin_zinnia/entry_detail.html
cmsplugin_zinnia/templates/cmsplugin_zinnia/entry_list.html
cmsplugin_zinnia/templates/cmsplugin_zinnia/entry_slider.html
cmsplugin_zinnia/templates/cmsplugin_zinnia/search_form.html
cmsplugin_zinnia/templates/cmsplugin_zinnia/tag_cloud.html
cmsplugin_zinnia/templates/cmsplugin_zinnia/tools.html
demo_cmsplugin_zinnia/__init__.py
demo_cmsplugin_zinnia/settings.py
demo_cmsplugin_zinnia/urls.py
demo_cmsplugin_zinnia/media/.gitignore
demo_cmsplugin_zinnia/migrations/__init__.py
demo_cmsplugin_zinnia/migrations/zinnia/0001_initial.py
demo_cmsplugin_zinnia/migrations/zinnia/__init__.py
demo_cmsplugin_zinnia/static/css/screen.css
demo_cmsplugin_zinnia/static/sass/screen.scss
demo_cmsplugin_zinnia/static/sass/config/_base.scss
demo_cmsplugin_zinnia/static/sass/mixins/_suckerfish.scss
demo_cmsplugin_zinnia/static/sass/partials/_cms_compatibility.scss
demo_cmsplugin_zinnia/static/sass/partials/_menu.scss
